README.md
setup.py
mypytorch/__init__.py
mypytorch.egg-info/PKG-INFO
mypytorch.egg-info/SOURCES.txt
mypytorch.egg-info/dependency_links.txt
mypytorch.egg-info/top_level.txt
mypytorch/metrics/__init__.py
mypytorch/metrics/accuracy.py
mypytorch/metrics/metrics.py
mypytorch/models/__init__.py
mypytorch/models/myBaseModel.py
mypytorch/models/myModel.py
mypytorch/models/myModelES.py
mypytorch/models/myModelESLR.py
mypytorch/models/myModelLR.py
mypytorch/schedulers/LinearCosine.py
mypytorch/schedulers/__init__.py