Metadata-Version: 2.1
Name: mypytorch
Version: 0.0.5
Summary: My Pytorch bindings
Home-page: https://github.com/juansensio/mypytorch
Author: Juan Sensio
Author-email: juansensio03@gmail.com
License: MIT
Keywords: python,pytorch
Platform: UNKNOWN
Classifier: Development Status :: 3 - Alpha
Classifier: Intended Audience :: Developers
Classifier: Topic :: Software Development :: Build Tools
Classifier: License :: OSI Approved :: MIT License
Classifier: Programming Language :: Python :: 3.7
